[
  {
    "type": "Plane",
    "name": "Z_Area_0-2_ALand.001",
    "position": {
      "x": -370.75543,
      "y": 0.0,
      "z": -348.01291
    },
    "rotation": {
      "w": 1.0,
      "x": 0.0,
      "y": 0.0,
      "z": -0.0
    },
    "size": {
      "width": 84.283645,
      "height": 0.0,
      "depth": 54.999995
    }
  },
  {
    "type": "Plane",
    "name": "Z_Area_0-2_ALand.002",
    "position": {
      "x": -483.44656,
      "y": -4.96655,
      "z": -348.01291
    },
    "rotation": {
      "w": 0.99626,
      "x": -2e-5,
      "y": -0.00026,
      "z": 0.08641
    },
    "size": {
      "width": 28.882975,
      "height": 0.0,
      "depth": 54.999995
    }
  },
  {
    "type": "Plane",
    "name": "Z_Area_0-2_Plane.001",
    "position": {
      "x": -310.00406,
      "y": 0.19921,
      "z": -369.99567
    },
    "rotation": {
      "w": 1.0,
      "x": 0.0,
      "y": 0.0,
      "z": -0.0
    },
    "size": {
      "width": 22.96138,
      "height": 0.0,
      "depth": 1.5
    }
  },
  {
    "type": "Plane",
    "name": "Z_Area_0-2_Plane.002",
    "position": {
      "x": -379.23975,
      "y": 0.19921,
      "z": -369.99567
    },
    "rotation": {
      "w": 1.0,
      "x": 0.0,
      "y": 0.0,
      "z": -0.0
    },
    "size": {
      "width": 32.21818,
      "height": 0.0,
      "depth": 1.5
    }
  },
  {
    "type": "Plane",
    "name": "Z_Area_0-2_Plane.003",
    "position": {
      "x": -366.17111,
      "y": 0.19921,
      "z": -388.50912
    },
    "rotation": {
      "w": 1.0,
      "x": 0.0,
      "y": 0.0,
      "z": -0.0
    },
    "size": {
      "width": 63.800465,
      "height": 0.0,
      "depth": 1.5
    }
  },
  {
    "type": "Plane",
    "name": "Z_Area_0-2_Plane.004",
    "position": {
      "x": -331.48941,
      "y": 0.19921,
      "z": -330.00241
    },
    "rotation": {
      "w": 1.0,
      "x": 0.0,
      "y": 0.0,
      "z": -0.0
    },
    "size": {
      "width": 1.5,
      "height": 0.0,
      "depth": 23.010555
    }
  },
  {
    "type": "Plane",
    "name": "Z_Area_0-2_Plane.005",
    "position": {
      "x": -348.50507,
      "y": 0.19921,
      "z": -330.00241
    },
    "rotation": {
      "w": 1.0,
      "x": 0.0,
      "y": 0.0,
      "z": -0.0
    },
    "size": {
      "width": 1.5,
      "height": 0.0,
      "depth": 23.010555
    }
  },
  {
    "type": "Plane",
    "name": "Z_Area_0-2_Plane.006",
    "position": {
      "x": -391.5033,
      "y": 0.19921,
      "z": -330.00241
    },
    "rotation": {
      "w": 1.0,
      "x": 0.0,
      "y": 0.0,
      "z": -0.0
    },
    "size": {
      "width": 1.5,
      "height": 0.0,
      "depth": 23.010555
    }
  },
  {
    "type": "Plane",
    "name": "Z_Area_0-2_Plane.007",
    "position": {
      "x": -410.00256,
      "y": 0.19921,
      "z": -339.47739
    },
    "rotation": {
      "w": 1.0,
      "x": 0.0,
      "y": 0.0,
      "z": -0.0
    },
    "size": {
      "width": 1.5,
      "height": 0.0,
      "depth": 29.463455
    }
  },
  {
    "type": "Plane",
    "name": "Z_Area_0-2_Plane.008",
    "position": {
      "x": -428.50705,
      "y": 0.19921,
      "z": -340.01135
    },
    "rotation": {
      "w": 1.0,
      "x": 0.0,
      "y": 0.0,
      "z": -0.0
    },
    "size": {
      "width": 1.5,
      "height": 0.0,
      "depth": 47.317575
    }
  },
  {
    "type": "Plane",
    "name": "Z_Area_0-2_Plane.009",
    "position": {
      "x": -310.00406,
      "y": 0.19921,
      "z": -351.48935
    },
    "rotation": {
      "w": 1.0,
      "x": 0.0,
      "y": 0.0,
      "z": -0.0
    },
    "size": {
      "width": 20.306745,
      "height": 0.0,
      "depth": 1.5
    }
  },
  {
    "type": "Plane",
    "name": "Z_Area_0-2_Plane.010",
    "position": {
      "x": -310.00406,
      "y": 0.19921,
      "z": -308.49619
    },
    "rotation": {
      "w": 1.0,
      "x": 0.0,
      "y": 0.0,
      "z": -0.0
    },
    "size": {
      "width": 20.306745,
      "height": 0.0,
      "depth": 1.5
    }
  },
  {
    "type": "Plane",
    "name": "Z_Area_0-2_Plane.011",
    "position": {
      "x": -370.01947,
      "y": 0.19921,
      "z": -308.49619
    },
    "rotation": {
      "w": 1.0,
      "x": 0.0,
      "y": 0.0,
      "z": -0.0
    },
    "size": {
      "width": 20.306745,
      "height": 0.0,
      "depth": 1.5
    }
  },
  {
    "type": "Plane",
    "name": "Z_Area_0-2_Plane.012",
    "position": {
      "x": -370.03244,
      "y": 0.19921,
      "z": -351.48935
    },
    "rotation": {
      "w": 1.0,
      "x": 0.0,
      "y": 0.0,
      "z": -0.0
    },
    "size": {
      "width": 20.306745,
      "height": 0.0,
      "depth": 1.5
    }
  },
  {
    "type": "Plane",
    "name": "Z_Area_0-2_Plane.013",
    "position": {
      "x": -322.64893,
      "y": 0.19921,
      "z": -313.12512
    },
    "rotation": {
      "w": 1.0,
      "x": 0.0,
      "y": 0.0,
      "z": -0.0
    },
    "size": {
      "width": 4.993335,
      "height": 0.0,
      "depth": 1.5
    }
  },
  {
    "type": "Plane",
    "name": "Z_Area_0-2_Plane.014",
    "position": {
      "x": -353.181,
      "y": 0.19921,
      "z": -333.30206
    },
    "rotation": {
      "w": 0.70711,
      "x": 0.0,
      "y": 0.70711,
      "z": -0.0
    },
    "size": {
      "width": 4.993335,
      "height": 0.0,
      "depth": 1.5
    }
  },
  {
    "type": "Solid",
    "name": "Z_Area_0-2_Solid.001",
    "position": {
      "x": -399.52231,
      "y": 3.28555,
      "z": -369.97427
    },
    "rotation": {
      "w": 0.70712,
      "x": 0.0,
      "y": 0.70709,
      "z": -0.0
    },
    "size": {
      "width": 0.2,
      "height": 2.93615,
      "depth": 0.2
    }
  },
  {
    "type": "Solid",
    "name": "Z_Area_0-2_Solid.002",
    "position": {
      "x": -310.14294,
      "y": 12.6258,
      "z": -345.04227
    },
    "rotation": {
      "w": 0.70712,
      "x": 0.0,
      "y": 0.70709,
      "z": -0.0
    },
    "size": {
      "width": 3.567405,
      "height": 9.211305,
      "depth": 18.711805
    }
  },
  {
    "type": "Solid",
    "name": "Z_Area_0-2_Solid.003",
    "position": {
      "x": -310.14294,
      "y": 12.6258,
      "z": -330.53748
    },
    "rotation": {
      "w": 0.70712,
      "x": 0.0,
      "y": 0.70709,
      "z": -0.0
    },
    "size": {
      "width": 3.567405,
      "height": 9.211305,
      "depth": 18.711805
    }
  },
  {
    "type": "Solid",
    "name": "Z_Area_0-2_Solid.004",
    "position": {
      "x": -310.08313,
      "y": 12.6258,
      "z": -337.89993
    },
    "rotation": {
      "w": 0.70712,
      "x": 0.0,
      "y": 0.70709,
      "z": -0.0
    },
    "size": {
      "width": 3.567405,
      "height": 9.211305,
      "depth": 14.941065
    }
  },
  {
    "type": "Solid",
    "name": "Z_Area_0-2_Solid.005",
    "position": {
      "x": -322.61646,
      "y": 6.80349,
      "z": -318.12314
    },
    "rotation": {
      "w": 0.70712,
      "x": 0.0,
      "y": 0.70709,
      "z": -0.0
    },
    "size": {
      "width": 3.453875,
      "height": 6.69741,
      "depth": 4.96048
    }
  },
  {
    "type": "Solid",
    "name": "Z_Area_0-2_Solid.006",
    "position": {
      "x": -322.61646,
      "y": 9.33927,
      "z": -313.32346
    },
    "rotation": {
      "w": 0.70712,
      "x": 0.0,
      "y": 0.70709,
      "z": -0.0
    },
    "size": {
      "width": 1.657995,
      "height": 4.16313,
      "depth": 4.96048
    }
  },
  {
    "type": "Solid",
    "name": "Z_Area_0-2_Solid.007",
    "position": {
      "x": -327.3331,
      "y": 2.66295,
      "z": -311.93567
    },
    "rotation": {
      "w": 0.70712,
      "x": 0.0,
      "y": 0.70709,
      "z": -0.0
    },
    "size": {
      "width": 0.281715,
      "height": 2.478515,
      "depth": 0.27494
    }
  },
  {
    "type": "Solid",
    "name": "Z_Area_0-2_Solid.008",
    "position": {
      "x": -317.95251,
      "y": 2.66295,
      "z": -311.93567
    },
    "rotation": {
      "w": 0.70712,
      "x": 0.0,
      "y": 0.70709,
      "z": -0.0
    },
    "size": {
      "width": 0.281715,
      "height": 2.478515,
      "depth": 0.27494
    }
  },
  {
    "type": "Solid",
    "name": "Z_Area_0-2_Solid.009",
    "position": {
      "x": -302.13806,
      "y": 2.73978,
      "z": -320.46213
    },
    "rotation": {
      "w": 1.0,
      "x": 0.0,
      "y": -1e-5,
      "z": -0.0
    },
    "size": {
      "width": 9.927635,
      "height": 2.769445,
      "depth": 3.934105
    }
  },
  {
    "type": "Solid",
    "name": "Z_Area_0-2_Solid.010",
    "position": {
      "x": -299.34656,
      "y": 2.32643,
      "z": -312.23984
    },
    "rotation": {
      "w": 1.0,
      "x": 0.0,
      "y": -1e-5,
      "z": -0.0
    },
    "size": {
      "width": 0.49201,
      "height": 2.18588,
      "depth": 0.46922
    }
  },
  {
    "type": "Solid",
    "name": "Z_Area_0-2_Solid.011",
    "position": {
      "x": -292.86017,
      "y": 2.32643,
      "z": -312.23969
    },
    "rotation": {
      "w": 1.0,
      "x": 0.0,
      "y": -1e-5,
      "z": -0.0
    },
    "size": {
      "width": 0.49201,
      "height": 2.18588,
      "depth": 0.46922
    }
  },
  {
    "type": "Solid",
    "name": "Z_Area_0-2_Solid.012",
    "position": {
      "x": -296.10782,
      "y": 5.03351,
      "z": -313.96844
    },
    "rotation": {
      "w": 1.0,
      "x": 0.0,
      "y": -1e-5,
      "z": -0.0
    },
    "size": {
      "width": 3.99516,
      "height": 0.47416,
      "depth": 2.5078
    }
  },
  {
    "type": "Solid",
    "name": "Z_Area_0-2_Solid.013",
    "position": {
      "x": -351.99158,
      "y": 2.66295,
      "z": -337.99847
    },
    "rotation": {
      "w": 2e-5,
      "x": 0.0,
      "y": 1.0,
      "z": -0.0
    },
    "size": {
      "width": 0.281715,
      "height": 2.478515,
      "depth": 0.27494
    }
  },
  {
    "type": "Solid",
    "name": "Z_Area_0-2_Solid.014",
    "position": {
      "x": -351.99152,
      "y": 2.66295,
      "z": -328.61789
    },
    "rotation": {
      "w": 2e-5,
      "x": 0.0,
      "y": 1.0,
      "z": -0.0
    },
    "size": {
      "width": 0.281715,
      "height": 2.478515,
      "depth": 0.27494
    }
  },
  {
    "type": "Solid",
    "name": "Z_Area_0-2_Solid.015",
    "position": {
      "x": -353.37933,
      "y": 9.33927,
      "z": -333.33453
    },
    "rotation": {
      "w": 2e-5,
      "x": 0.0,
      "y": 1.0,
      "z": -0.0
    },
    "size": {
      "width": 1.65799,
      "height": 4.16313,
      "depth": 4.96048
    }
  },
  {
    "type": "Solid",
    "name": "Z_Area_0-2_Solid.016",
    "position": {
      "x": -358.17902,
      "y": 6.80349,
      "z": -333.33453
    },
    "rotation": {
      "w": 2e-5,
      "x": 0.0,
      "y": 1.0,
      "z": -0.0
    },
    "size": {
      "width": 3.453875,
      "height": 6.69741,
      "depth": 4.96048
    }
  },
  {
    "type": "Solid",
    "name": "Z_Area_0-2_Solid.017",
    "position": {
      "x": -356.83615,
      "y": 4.98364,
      "z": -343.81107
    },
    "rotation": {
      "w": 2e-5,
      "x": 0.0,
      "y": 1.0,
      "z": -0.0
    },
    "size": {
      "width": 5.093455,
      "height": 4.69558,
      "depth": 4.682015
    }
  },
  {
    "type": "Solid",
    "name": "Z_Area_0-2_Solid.018",
    "position": {
      "x": -377.14319,
      "y": 11.00685,
      "z": -340.6188
    },
    "rotation": {
      "w": 0.70713,
      "x": 0.0,
      "y": -0.70708,
      "z": -0.0
    },
    "size": {
      "width": 8.1321,
      "height": 11.14538,
      "depth": 8.00072
    }
  },
  {
    "type": "Solid",
    "name": "Z_Area_0-2_Solid.019",
    "position": {
      "x": -377.14319,
      "y": 11.00685,
      "z": -340.6188
    },
    "rotation": {
      "w": 0.70713,
      "x": 0.0,
      "y": -0.70708,
      "z": -0.0
    },
    "size": {
      "width": 4.12075,
      "height": 11.14538,
      "depth": 11.28644
    }
  },
  {
    "type": "Solid",
    "name": "Z_Area_0-2_Solid.020",
    "position": {
      "x": -364.84958,
      "y": 5.39094,
      "z": -313.46225
    },
    "rotation": {
      "w": 1.0,
      "x": 0.0,
      "y": -3e-5,
      "z": -0.0
    },
    "size": {
      "width": 6.040105,
      "height": 5.36033,
      "depth": 1.73466
    }
  },
  {
    "type": "Solid",
    "name": "Z_Area_0-2_Solid.021",
    "position": {
      "x": -356.14798,
      "y": 5.39094,
      "z": -315.20209
    },
    "rotation": {
      "w": 1.0,
      "x": 0.0,
      "y": -3e-5,
      "z": -0.0
    },
    "size": {
      "width": 2.65419,
      "height": 5.36033,
      "depth": 1.73466
    }
  },
  {
    "type": "Solid",
    "name": "Z_Area_0-2_Solid.022",
    "position": {
      "x": -352.69409,
      "y": 5.39239,
      "z": -320.44153
    },
    "rotation": {
      "w": 1.0,
      "x": 0.0,
      "y": -3e-5,
      "z": -0.0
    },
    "size": {
      "width": 0.915685,
      "height": 5.36033,
      "depth": 3.432855
    }
  },
  {
    "type": "Solid",
    "name": "Z_Area_0-2_Solid.023",
    "position": {
      "x": -363.14316,
      "y": 5.39094,
      "z": -321.32651
    },
    "rotation": {
      "w": 1.0,
      "x": 0.0,
      "y": -3e-5,
      "z": -0.0
    },
    "size": {
      "width": 9.554465,
      "height": 5.36033,
      "depth": 6.092195
    }
  },
  {
    "type": "Solid",
    "name": "Z_Area_0-2_Solid.024",
    "position": {
      "x": -379.89496,
      "y": 7.31206,
      "z": -320.44687
    },
    "rotation": {
      "w": 1.0,
      "x": 0.0,
      "y": -3e-5,
      "z": -0.0
    },
    "size": {
      "width": 5.055275,
      "height": 7.28175,
      "depth": 7.61158
    }
  },
  {
    "type": "Solid",
    "name": "Z_Area_0-2_Solid.025",
    "position": {
      "x": -385.75375,
      "y": 7.31206,
      "z": -320.44687
    },
    "rotation": {
      "w": 1.0,
      "x": 0.0,
      "y": -3e-5,
      "z": -0.0
    },
    "size": {
      "width": 0.8394,
      "height": 7.28175,
      "depth": 2.213735
    }
  },
  {
    "type": "Solid",
    "name": "Z_Area_0-2_Solid.026",
    "position": {
      "x": -434.2825,
      "y": 2.28445,
      "z": -317.50485
    },
    "rotation": {
      "w": 0.70712,
      "x": 0.0,
      "y": 0.70709,
      "z": -0.0
    },
    "size": {
      "width": 0.05,
      "height": 2.231425,
      "depth": 0.05
    }
  },
  {
    "type": "Solid",
    "name": "Z_Area_0-2_Solid.027",
    "position": {
      "x": -430.27823,
      "y": 2.28445,
      "z": -317.49954
    },
    "rotation": {
      "w": 0.70712,
      "x": 0.0,
      "y": 0.70709,
      "z": -0.0
    },
    "size": {
      "width": 0.05,
      "height": 2.231425,
      "depth": 0.05
    }
  }
]
