[
  {
    "type": "Plane",
    "name": "Z_Area_2-7_ALand.001",
    "position": {
      "x": 0.0,
      "y": 0.0,
      "z": 644.229
    },
    "rotation": {
      "w": 1.0,
      "x": 0.0,
      "y": 0.0,
      "z": -0.0
    },
    "size": {
      "width": 100.0,
      "height": 0.0,
      "depth": 57.257095
    }
  },
  {
    "type": "Plane",
    "name": "Z_Area_2-7_ALand.002",
    "position": {
      "x": -0.05105,
      "y": 15.00221,
      "z": 595.9212
    },
    "rotation": {
      "w": 1.0,
      "x": 0.0,
      "y": 0.0,
      "z": -0.0
    },
    "size": {
      "width": 20.036015,
      "height": 0.0,
      "depth": 98.90162
    }
  },
  {
    "type": "Circle",
    "name": "Z_Area_2-7_Circle.001",
    "position": {
      "x": -54.23315,
      "y": 0.48827,
      "z": 691.62744
    },
    "rotation": {
      "w": 0.70713,
      "x": 0.70708,
      "y": 0.0,
      "z": -0.0
    },
    "size": {
      "width": 1.35,
      "height": 12.24649,
      "depth": 1.35
    }
  },
  {
    "type": "Circle",
    "name": "Z_Area_2-7_Circle.002",
    "position": {
      "x": -58.24385,
      "y": 0.48827,
      "z": 691.62744
    },
    "rotation": {
      "w": 0.70713,
      "x": 0.70708,
      "y": 0.0,
      "z": -0.0
    },
    "size": {
      "width": 1.35,
      "height": 12.24649,
      "depth": 1.35
    }
  },
  {
    "type": "Circle",
    "name": "Z_Area_2-7_Circle.003",
    "position": {
      "x": -72.0355,
      "y": 2.57358,
      "z": 701.96906
    },
    "rotation": {
      "w": 1.0,
      "x": 0.0,
      "y": 0.0,
      "z": -0.0
    },
    "size": {
      "width": 5.0,
      "height": 2.527025,
      "depth": 5.0
    }
  },
  {
    "type": "Circle",
    "name": "Z_Area_2-7_Circle.004",
    "position": {
      "x": -72.02338,
      "y": 2.60241,
      "z": 680.00818
    },
    "rotation": {
      "w": 1.0,
      "x": 0.0,
      "y": 0.0,
      "z": -0.0
    },
    "size": {
      "width": 5.0,
      "height": 2.527025,
      "depth": 5.0
    }
  },
  {
    "type": "Circle",
    "name": "Z_Area_2-7_Circle.005",
    "position": {
      "x": -72.0355,
      "y": 2.57358,
      "z": 691.01544
    },
    "rotation": {
      "w": 1.0,
      "x": 0.0,
      "y": 0.0,
      "z": -0.0
    },
    "size": {
      "width": 5.0,
      "height": 2.527025,
      "depth": 5.0
    }
  },
  {
    "type": "Plane",
    "name": "Z_Area_2-7_Plane.001",
    "position": {
      "x": -51.465,
      "y": 0.19893,
      "z": 628.47449
    },
    "rotation": {
      "w": 1.0,
      "x": 0.0,
      "y": 0.0,
      "z": -0.0
    },
    "size": {
      "width": 1.49874,
      "height": 0.0,
      "depth": 21.511995
    }
  },
  {
    "type": "Plane",
    "name": "Z_Area_2-7_Plane.002",
    "position": {
      "x": -88.50559,
      "y": 0.19893,
      "z": 628.47449
    },
    "rotation": {
      "w": 1.0,
      "x": 0.0,
      "y": 0.0,
      "z": -0.0
    },
    "size": {
      "width": 1.49874,
      "height": 0.0,
      "depth": 21.511995
    }
  },
  {
    "type": "Plane",
    "name": "Z_Area_2-7_Plane.003",
    "position": {
      "x": -48.49712,
      "y": 0.19893,
      "z": 690.02362
    },
    "rotation": {
      "w": 1.0,
      "x": 0.0,
      "y": 0.0,
      "z": -0.0
    },
    "size": {
      "width": 1.49874,
      "height": 0.0,
      "depth": 22.986235
    }
  },
  {
    "type": "Plane",
    "name": "Z_Area_2-7_Plane.004",
    "position": {
      "x": -48.49712,
      "y": 0.19893,
      "z": 641.47455
    },
    "rotation": {
      "w": 1.0,
      "x": 0.0,
      "y": 0.0,
      "z": -0.0
    },
    "size": {
      "width": 1.49874,
      "height": 0.0,
      "depth": 11.50514
    }
  },
  {
    "type": "Plane",
    "name": "Z_Area_2-7_Plane.005",
    "position": {
      "x": -0.00459,
      "y": 15.19081,
      "z": 651.01929
    },
    "rotation": {
      "w": 1.0,
      "x": 0.0,
      "y": 0.0,
      "z": -0.0
    },
    "size": {
      "width": 1.49874,
      "height": 0.0,
      "depth": 44.344275
    }
  },
  {
    "type": "Plane",
    "name": "Z_Area_2-7_Plane.006",
    "position": {
      "x": -17.96756,
      "y": 15.19081,
      "z": 649.65039
    },
    "rotation": {
      "w": 1.0,
      "x": 0.0,
      "y": 0.0,
      "z": -0.0
    },
    "size": {
      "width": 0.9835,
      "height": 0.0,
      "depth": 46.853255
    }
  },
  {
    "type": "Plane",
    "name": "Z_Area_2-7_Plane.007",
    "position": {
      "x": 17.98388,
      "y": 15.19081,
      "z": 650.0481
    },
    "rotation": {
      "w": 1.0,
      "x": 0.0,
      "y": 0.0,
      "z": -0.0
    },
    "size": {
      "width": 0.9835,
      "height": 0.0,
      "depth": 47.2515
    }
  },
  {
    "type": "Plane",
    "name": "Z_Area_2-7_Plane.008",
    "position": {
      "x": 17.98388,
      "y": 15.19081,
      "z": 549.52527
    },
    "rotation": {
      "w": 1.0,
      "x": 0.0,
      "y": 0.0,
      "z": -0.0
    },
    "size": {
      "width": 0.9835,
      "height": 0.0,
      "depth": 54.956265
    }
  },
  {
    "type": "Plane",
    "name": "Z_Area_2-7_Plane.009",
    "position": {
      "x": -17.96756,
      "y": 15.19081,
      "z": 549.81018
    },
    "rotation": {
      "w": 1.0,
      "x": 0.0,
      "y": 0.0,
      "z": -0.0
    },
    "size": {
      "width": 0.9835,
      "height": 0.0,
      "depth": 54.956265
    }
  },
  {
    "type": "Plane",
    "name": "Z_Area_2-7_Plane.010",
    "position": {
      "x": -0.00459,
      "y": 15.19081,
      "z": 550.86969
    },
    "rotation": {
      "w": 1.0,
      "x": 0.0,
      "y": 0.0,
      "z": -0.0
    },
    "size": {
      "width": 1.49874,
      "height": 0.0,
      "depth": 56.36139
    }
  },
  {
    "type": "Plane",
    "name": "Z_Area_2-7_Plane.011",
    "position": {
      "x": -31.4986,
      "y": 0.19893,
      "z": 679.97125
    },
    "rotation": {
      "w": 1.0,
      "x": 0.0,
      "y": 0.0,
      "z": -0.0
    },
    "size": {
      "width": 1.49874,
      "height": 0.0,
      "depth": 33.023605
    }
  },
  {
    "type": "Plane",
    "name": "Z_Area_2-7_Plane.012",
    "position": {
      "x": -57.95202,
      "y": 0.19893,
      "z": 648.49402
    },
    "rotation": {
      "w": 1.0,
      "x": 0.0,
      "y": 0.0,
      "z": -0.0
    },
    "size": {
      "width": 5.065215,
      "height": 0.0,
      "depth": 1.5
    }
  },
  {
    "type": "Plane",
    "name": "Z_Area_2-7_Plane.013",
    "position": {
      "x": -82.06817,
      "y": 0.19893,
      "z": 648.49402
    },
    "rotation": {
      "w": 1.0,
      "x": 0.0,
      "y": 0.0,
      "z": -0.0
    },
    "size": {
      "width": 5.065215,
      "height": 0.0,
      "depth": 1.5
    }
  },
  {
    "type": "Plane",
    "name": "Z_Area_2-7_Plane.014",
    "position": {
      "x": -69.99133,
      "y": 0.19893,
      "z": 609.99292
    },
    "rotation": {
      "w": 1.0,
      "x": 0.0,
      "y": 0.0,
      "z": -0.0
    },
    "size": {
      "width": 17.214575,
      "height": 0.0,
      "depth": 3.0
    }
  },
  {
    "type": "Plane",
    "name": "Z_Area_2-7_Plane.015",
    "position": {
      "x": -13.24623,
      "y": 0.19893,
      "z": 631.50037
    },
    "rotation": {
      "w": 1.0,
      "x": 0.0,
      "y": 0.0,
      "z": -0.0
    },
    "size": {
      "width": 34.170495,
      "height": 0.0,
      "depth": 1.5
    }
  },
  {
    "type": "Plane",
    "name": "Z_Area_2-7_Plane.016",
    "position": {
      "x": 60.38285,
      "y": 0.19893,
      "z": 631.50037
    },
    "rotation": {
      "w": 1.0,
      "x": 0.0,
      "y": 0.0,
      "z": -0.0
    },
    "size": {
      "width": 39.80258,
      "height": 0.0,
      "depth": 1.5
    }
  },
  {
    "type": "Plane",
    "name": "Z_Area_2-7_Plane.017",
    "position": {
      "x": 60.38285,
      "y": 0.19893,
      "z": 648.50299
    },
    "rotation": {
      "w": 1.0,
      "x": 0.0,
      "y": 0.0,
      "z": -0.0
    },
    "size": {
      "width": 39.80258,
      "height": 0.0,
      "depth": 1.5
    }
  },
  {
    "type": "Plane",
    "name": "Z_Area_2-7_Plane.018",
    "position": {
      "x": -4.82056,
      "y": 0.19893,
      "z": 648.50299
    },
    "rotation": {
      "w": 1.0,
      "x": 0.0,
      "y": 0.0,
      "z": -0.0
    },
    "size": {
      "width": 25.67308,
      "height": 0.0,
      "depth": 1.5
    }
  },
  {
    "type": "Plane",
    "name": "Z_Area_2-7_Plane.019",
    "position": {
      "x": 43.87226,
      "y": 0.91327,
      "z": 652.6571
    },
    "rotation": {
      "w": 0.9684,
      "x": -0.24942,
      "y": 0.0,
      "z": -0.0
    },
    "size": {
      "width": 7.565755,
      "height": 0.0,
      "depth": 1.5
    }
  },
  {
    "type": "Solid",
    "name": "Z_Area_2-7_Solid.001",
    "position": {
      "x": 20.5391,
      "y": 14.55729,
      "z": 663.31854
    },
    "rotation": {
      "w": 1.0,
      "x": 0.0,
      "y": 0.0,
      "z": -0.0
    },
    "size": {
      "width": 1.485745,
      "height": 1.450895,
      "depth": 52.5
    }
  },
  {
    "type": "Solid",
    "name": "Z_Area_2-7_Solid.002",
    "position": {
      "x": 20.5391,
      "y": 14.55729,
      "z": 559.90839
    },
    "rotation": {
      "w": 1.0,
      "x": 0.0,
      "y": 0.0,
      "z": -0.0
    },
    "size": {
      "width": 1.485745,
      "height": 1.450895,
      "depth": 52.5
    }
  },
  {
    "type": "Solid",
    "name": "Z_Area_2-7_Solid.003",
    "position": {
      "x": -20.49203,
      "y": 14.55729,
      "z": 559.42029
    },
    "rotation": {
      "w": 1.0,
      "x": 0.0,
      "y": 0.0,
      "z": -0.0
    },
    "size": {
      "width": 1.485745,
      "height": 1.450895,
      "depth": 52.5
    }
  },
  {
    "type": "Solid",
    "name": "Z_Area_2-7_Solid.004",
    "position": {
      "x": -20.49203,
      "y": 14.55729,
      "z": 663.08807
    },
    "rotation": {
      "w": 1.0,
      "x": 0.0,
      "y": 0.0,
      "z": -0.0
    },
    "size": {
      "width": 1.485745,
      "height": 1.450895,
      "depth": 52.5
    }
  },
  {
    "type": "Solid",
    "name": "Z_Area_2-7_Solid.005",
    "position": {
      "x": -18.49545,
      "y": 6.56744,
      "z": 600.00043
    },
    "rotation": {
      "w": 1.0,
      "x": 0.0,
      "y": 0.0,
      "z": -0.0
    },
    "size": {
      "width": 1.03929,
      "height": 6.720645,
      "depth": 1.730745
    }
  },
  {
    "type": "Solid",
    "name": "Z_Area_2-7_Solid.006",
    "position": {
      "x": 18.48393,
      "y": 6.56744,
      "z": 600.00043
    },
    "rotation": {
      "w": 1.0,
      "x": 0.0,
      "y": 0.0,
      "z": -0.0
    },
    "size": {
      "width": 1.03929,
      "height": 6.720645,
      "depth": 1.730745
    }
  },
  {
    "type": "Solid",
    "name": "Z_Area_2-7_Solid.007",
    "position": {
      "x": 18.48393,
      "y": 6.56744,
      "z": 653.0224
    },
    "rotation": {
      "w": 1.0,
      "x": 0.0,
      "y": 0.0,
      "z": -0.0
    },
    "size": {
      "width": 1.03929,
      "height": 6.720645,
      "depth": 1.730745
    }
  },
  {
    "type": "Solid",
    "name": "Z_Area_2-7_Solid.008",
    "position": {
      "x": -18.49545,
      "y": 6.56744,
      "z": 653.0224
    },
    "rotation": {
      "w": 1.0,
      "x": 0.0,
      "y": 0.0,
      "z": -0.0
    },
    "size": {
      "width": 1.03929,
      "height": 6.720645,
      "depth": 1.730745
    }
  },
  {
    "type": "Solid",
    "name": "Z_Area_2-7_Solid.009",
    "position": {
      "x": -61.49238,
      "y": 1.39527,
      "z": 648.95465
    },
    "rotation": {
      "w": 1.0,
      "x": 0.0,
      "y": 0.0,
      "z": -0.0
    },
    "size": {
      "width": 0.3,
      "height": 1.19039,
      "depth": 0.2
    }
  },
  {
    "type": "Solid",
    "name": "Z_Area_2-7_Solid.010",
    "position": {
      "x": -78.48503,
      "y": 1.39527,
      "z": 648.95465
    },
    "rotation": {
      "w": 1.0,
      "x": 0.0,
      "y": 0.0,
      "z": -0.0
    },
    "size": {
      "width": 0.3,
      "height": 1.19039,
      "depth": 0.2
    }
  },
  {
    "type": "Solid",
    "name": "Z_Area_2-7_Solid.011",
    "position": {
      "x": -90.0246,
      "y": 4.21589,
      "z": 657.81543
    },
    "rotation": {
      "w": 0.70703,
      "x": 0.0,
      "y": 0.70719,
      "z": -0.0
    },
    "size": {
      "width": 4.3097,
      "height": 4.045225,
      "depth": 11.51832
    }
  },
  {
    "type": "Solid",
    "name": "Z_Area_2-7_Solid.012",
    "position": {
      "x": -90.07224,
      "y": 2.39218,
      "z": 673.66937
    },
    "rotation": {
      "w": 0.70713,
      "x": 0.0,
      "y": -0.70708,
      "z": -0.0
    },
    "size": {
      "width": 4.432145,
      "height": 2.202,
      "depth": 7.67257
    }
  },
  {
    "type": "Solid",
    "name": "Z_Area_2-7_Solid.013",
    "position": {
      "x": -88.72755,
      "y": 6.00483,
      "z": 692.8689
    },
    "rotation": {
      "w": 0.70713,
      "x": 0.0,
      "y": -0.70708,
      "z": -0.0
    },
    "size": {
      "width": 13.47216,
      "height": 5.992435,
      "depth": 9.47143
    }
  },
  {
    "type": "Solid",
    "name": "Z_Area_2-7_Solid.014",
    "position": {
      "x": -98.67902,
      "y": 2.87052,
      "z": 643.30481
    },
    "rotation": {
      "w": 1.0,
      "x": 0.0,
      "y": -7e-5,
      "z": -0.0
    },
    "size": {
      "width": 2.75287,
      "height": 2.878865,
      "depth": 6.361515
    }
  },
  {
    "type": "Solid",
    "name": "Z_Area_2-7_Solid.017",
    "position": {
      "x": -62.86633,
      "y": 0.92415,
      "z": 694.22925
    },
    "rotation": {
      "w": 1.0,
      "x": 0.0,
      "y": 0.0,
      "z": -0.0
    },
    "size": {
      "width": 1.258685,
      "height": 0.98477,
      "depth": 9.32451
    }
  },
  {
    "type": "Solid",
    "name": "Z_Area_2-7_Solid.019",
    "position": {
      "x": 28.01807,
      "y": 4.74724,
      "z": 663.85651
    },
    "rotation": {
      "w": 0.70703,
      "x": 0.0,
      "y": 0.70719,
      "z": -0.0
    },
    "size": {
      "width": 11.96265,
      "height": 4.749415,
      "depth": 5.9305
    }
  },
  {
    "type": "Solid",
    "name": "Z_Area_2-7_Solid.020",
    "position": {
      "x": 57.5777,
      "y": 18.59379,
      "z": 660.69666
    },
    "rotation": {
      "w": 0.70708,
      "x": 0.0,
      "y": 0.70713,
      "z": -0.0
    },
    "size": {
      "width": 6.539435,
      "height": 18.6301,
      "depth": 3.442465
    }
  },
  {
    "type": "Solid",
    "name": "Z_Area_2-7_Solid.021",
    "position": {
      "x": 68.12398,
      "y": 18.59379,
      "z": 658.07391
    },
    "rotation": {
      "w": 0.70708,
      "x": 0.0,
      "y": 0.70713,
      "z": -0.0
    },
    "size": {
      "width": 6.539435,
      "height": 18.6301,
      "depth": 3.442465
    }
  },
  {
    "type": "Solid",
    "name": "Z_Area_2-7_Solid.022",
    "position": {
      "x": 62.81522,
      "y": 18.59379,
      "z": 659.36877
    },
    "rotation": {
      "w": 0.70708,
      "x": 0.0,
      "y": 0.70713,
      "z": -0.0
    },
    "size": {
      "width": 5.238985,
      "height": 18.6301,
      "depth": 2.001245
    }
  },
  {
    "type": "Solid",
    "name": "Z_Area_2-7_Solid.023",
    "position": {
      "x": 90.39139,
      "y": 6.64783,
      "z": 682.16736
    },
    "rotation": {
      "w": 1.0,
      "x": 0.0,
      "y": 0.0,
      "z": -0.0
    },
    "size": {
      "width": 5.238985,
      "height": 6.32994,
      "depth": 2.001245
    }
  },
  {
    "type": "Solid",
    "name": "Z_Area_2-7_Solid.024",
    "position": {
      "x": 91.68593,
      "y": 6.64783,
      "z": 687.4762
    },
    "rotation": {
      "w": 1.0,
      "x": 0.0,
      "y": 0.0,
      "z": -0.0
    },
    "size": {
      "width": 6.539435,
      "height": 6.32994,
      "depth": 3.442465
    }
  },
  {
    "type": "Solid",
    "name": "Z_Area_2-7_Solid.025",
    "position": {
      "x": 89.06382,
      "y": 6.64783,
      "z": 676.92975
    },
    "rotation": {
      "w": 1.0,
      "x": 0.0,
      "y": 0.0,
      "z": -0.0
    },
    "size": {
      "width": 6.539435,
      "height": 6.32994,
      "depth": 3.442465
    }
  },
  {
    "type": "Solid",
    "name": "Z_Area_2-7_Solid.026",
    "position": {
      "x": 94.31374,
      "y": 12.62962,
      "z": 660.43073
    },
    "rotation": {
      "w": 1.0,
      "x": 0.0,
      "y": 0.0,
      "z": -0.0
    },
    "size": {
      "width": 3.659145,
      "height": 9.253075,
      "depth": 9.054395
    }
  },
  {
    "type": "Solid",
    "name": "Z_Area_2-7_Solid.027",
    "position": {
      "x": 79.85314,
      "y": 12.62962,
      "z": 660.43073
    },
    "rotation": {
      "w": 1.0,
      "x": 0.0,
      "y": 0.0,
      "z": -0.0
    },
    "size": {
      "width": 3.659145,
      "height": 9.253075,
      "depth": 9.054395
    }
  },
  {
    "type": "Solid",
    "name": "Z_Area_2-7_Solid.028",
    "position": {
      "x": 87.08706,
      "y": 12.62962,
      "z": 660.43073
    },
    "rotation": {
      "w": 1.0,
      "x": 0.0,
      "y": 0.0,
      "z": -0.0
    },
    "size": {
      "width": 3.659145,
      "height": 9.253075,
      "depth": 5.390505
    }
  },
  {
    "type": "Solid",
    "name": "Z_Area_2-7_Solid.029",
    "position": {
      "x": 44.04121,
      "y": 6.91548,
      "z": 667.16846
    },
    "rotation": {
      "w": 0.70713,
      "x": 0.0,
      "y": -0.70708,
      "z": -0.0
    },
    "size": {
      "width": 9.043785,
      "height": 5.191985,
      "depth": 7.201105
    }
  },
  {
    "type": "Solid",
    "name": "Z_Area_2-7_Solid.030",
    "position": {
      "x": 44.01389,
      "y": 0.98065,
      "z": 665.25641
    },
    "rotation": {
      "w": 0.70713,
      "x": 0.0,
      "y": -0.70708,
      "z": -0.0
    },
    "size": {
      "width": 11.44462,
      "height": 0.804585,
      "depth": 7.67442
    }
  },
  {
    "type": "Solid",
    "name": "Z_Area_2-7_Solid.031",
    "position": {
      "x": 37.28428,
      "y": 4.46823,
      "z": 654.73199
    },
    "rotation": {
      "w": 1.0,
      "x": 0.0,
      "y": 0.0,
      "z": -0.0
    },
    "size": {
      "width": 0.352085,
      "height": 4.496235,
      "depth": 0.355425
    }
  },
  {
    "type": "Solid",
    "name": "Z_Area_2-7_Solid.032",
    "position": {
      "x": 41.80048,
      "y": 4.46823,
      "z": 654.73199
    },
    "rotation": {
      "w": 1.0,
      "x": 0.0,
      "y": 0.0,
      "z": -0.0
    },
    "size": {
      "width": 0.352085,
      "height": 4.496235,
      "depth": 0.355425
    }
  },
  {
    "type": "Solid",
    "name": "Z_Area_2-7_Solid.033",
    "position": {
      "x": 46.27537,
      "y": 4.46823,
      "z": 654.73199
    },
    "rotation": {
      "w": 1.0,
      "x": 0.0,
      "y": 0.0,
      "z": -0.0
    },
    "size": {
      "width": 0.352085,
      "height": 4.496235,
      "depth": 0.355425
    }
  },
  {
    "type": "Solid",
    "name": "Z_Area_2-7_Solid.034",
    "position": {
      "x": 50.80042,
      "y": 4.46823,
      "z": 654.73199
    },
    "rotation": {
      "w": 1.0,
      "x": 0.0,
      "y": 0.0,
      "z": -0.0
    },
    "size": {
      "width": 0.352085,
      "height": 4.496235,
      "depth": 0.355425
    }
  }
]
