[
  {
    "type": "Plane",
    "name": "Z_Area_2-3_ALand.001",
    "position": {
      "x": 0.0,
      "y": 0.0,
      "z": -200.0
    },
    "rotation": {
      "w": 1.0,
      "x": 0.0,
      "y": 0.0,
      "z": -0.0
    },
    "size": {
      "width": 102.5,
      "height": 0.0,
      "depth": 102.5
    }
  },
  {
    "type": "Circle",
    "name": "Z_Area_2-3_Circle.001",
    "position": {
      "x": 62.25962,
      "y": 2.29543,
      "z": -197.85818
    },
    "rotation": {
      "w": 1.0,
      "x": 0.0,
      "y": 0.0,
      "z": -0.0
    },
    "size": {
      "width": 3.0,
      "height": 2.231305,
      "depth": 3.0
    }
  },
  {
    "type": "Circle",
    "name": "Z_Area_2-3_Circle.002",
    "position": {
      "x": 27.8178,
      "y": 2.29543,
      "z": -222.46574
    },
    "rotation": {
      "w": 1.0,
      "x": 0.0,
      "y": 0.0,
      "z": -0.0
    },
    "size": {
      "width": 3.0,
      "height": 2.231305,
      "depth": 3.0
    }
  },
  {
    "type": "Circle",
    "name": "Z_Area_2-3_Circle.003",
    "position": {
      "x": -57.4174,
      "y": 2.79997,
      "z": -202.75662
    },
    "rotation": {
      "w": 1.0,
      "x": 0.0,
      "y": 0.0,
      "z": -0.0
    },
    "size": {
      "width": 9.4,
      "height": 3.11871,
      "depth": 9.4
    }
  },
  {
    "type": "Plane",
    "name": "Z_Area_2-3_Plane.001",
    "position": {
      "x": 0.00434,
      "y": 0.19921,
      "z": -270.01266
    },
    "rotation": {
      "w": 1.0,
      "x": 0.0,
      "y": 0.0,
      "z": -0.0
    },
    "size": {
      "width": 1.5,
      "height": 0.0,
      "depth": 19.98745
    }
  },
  {
    "type": "Plane",
    "name": "Z_Area_2-3_Plane.002",
    "position": {
      "x": -18.49632,
      "y": 0.19921,
      "z": -269.99426
    },
    "rotation": {
      "w": 1.0,
      "x": 0.0,
      "y": 0.0,
      "z": -0.0
    },
    "size": {
      "width": 1.5,
      "height": 0.0,
      "depth": 23.0
    }
  },
  {
    "type": "Plane",
    "name": "Z_Area_2-3_Plane.003",
    "position": {
      "x": -71.50126,
      "y": 0.19921,
      "z": -269.99426
    },
    "rotation": {
      "w": 1.0,
      "x": 0.0,
      "y": 0.0,
      "z": -0.0
    },
    "size": {
      "width": 1.5,
      "height": 0.0,
      "depth": 23.0
    }
  },
  {
    "type": "Plane",
    "name": "Z_Area_2-3_Plane.004",
    "position": {
      "x": 18.50504,
      "y": 0.19921,
      "z": -269.99426
    },
    "rotation": {
      "w": 1.0,
      "x": 0.0,
      "y": 0.0,
      "z": -0.0
    },
    "size": {
      "width": 1.5,
      "height": 0.0,
      "depth": 23.0
    }
  },
  {
    "type": "Plane",
    "name": "Z_Area_2-3_Plane.005",
    "position": {
      "x": 71.5044,
      "y": 0.19921,
      "z": -269.99426
    },
    "rotation": {
      "w": 1.0,
      "x": 0.0,
      "y": 0.0,
      "z": -0.0
    },
    "size": {
      "width": 1.5,
      "height": 0.0,
      "depth": 23.0
    }
  },
  {
    "type": "Plane",
    "name": "Z_Area_2-3_Plane.006",
    "position": {
      "x": 88.50539,
      "y": 0.19921,
      "z": -239.93208
    },
    "rotation": {
      "w": 1.0,
      "x": 0.0,
      "y": 0.0,
      "z": -0.0
    },
    "size": {
      "width": 1.5,
      "height": 0.0,
      "depth": 50.215845
    }
  },
  {
    "type": "Plane",
    "name": "Z_Area_2-3_Plane.007",
    "position": {
      "x": 71.5044,
      "y": 0.19921,
      "z": -209.99854
    },
    "rotation": {
      "w": 1.0,
      "x": 0.0,
      "y": 0.0,
      "z": -0.0
    },
    "size": {
      "width": 1.5,
      "height": 0.0,
      "depth": 23.0
    }
  },
  {
    "type": "Plane",
    "name": "Z_Area_2-3_Plane.008",
    "position": {
      "x": 18.50282,
      "y": 0.19921,
      "z": -209.99854
    },
    "rotation": {
      "w": 1.0,
      "x": 0.0,
      "y": 0.0,
      "z": -0.0
    },
    "size": {
      "width": 1.5,
      "height": 0.0,
      "depth": 23.0
    }
  },
  {
    "type": "Plane",
    "name": "Z_Area_2-3_Plane.009",
    "position": {
      "x": -71.49624,
      "y": 0.19921,
      "z": -209.99854
    },
    "rotation": {
      "w": 1.0,
      "x": 0.0,
      "y": 0.0,
      "z": -0.0
    },
    "size": {
      "width": 1.5,
      "height": 0.0,
      "depth": 23.0
    }
  },
  {
    "type": "Plane",
    "name": "Z_Area_2-3_Plane.010",
    "position": {
      "x": -71.49624,
      "y": 0.19921,
      "z": -149.9913
    },
    "rotation": {
      "w": 1.0,
      "x": 0.0,
      "y": 0.0,
      "z": -0.0
    },
    "size": {
      "width": 1.5,
      "height": 0.0,
      "depth": 23.0
    }
  },
  {
    "type": "Plane",
    "name": "Z_Area_2-3_Plane.011",
    "position": {
      "x": -88.49472,
      "y": 0.19921,
      "z": -149.9913
    },
    "rotation": {
      "w": 1.0,
      "x": 0.0,
      "y": 0.0,
      "z": -0.0
    },
    "size": {
      "width": 1.5,
      "height": 0.0,
      "depth": 23.0
    }
  },
  {
    "type": "Plane",
    "name": "Z_Area_2-3_Plane.012",
    "position": {
      "x": -18.49328,
      "y": 0.19921,
      "z": -149.9913
    },
    "rotation": {
      "w": 1.0,
      "x": 0.0,
      "y": 0.0,
      "z": -0.0
    },
    "size": {
      "width": 1.5,
      "height": 0.0,
      "depth": 23.0
    }
  },
  {
    "type": "Plane",
    "name": "Z_Area_2-3_Plane.013",
    "position": {
      "x": 18.50214,
      "y": 0.19921,
      "z": -136.22876
    },
    "rotation": {
      "w": 1.0,
      "x": 0.0,
      "y": 0.0,
      "z": -0.0
    },
    "size": {
      "width": 1.5,
      "height": 0.0,
      "depth": 36.77983
    }
  },
  {
    "type": "Plane",
    "name": "Z_Area_2-3_Plane.014",
    "position": {
      "x": 71.50583,
      "y": 0.19921,
      "z": -136.22876
    },
    "rotation": {
      "w": 1.0,
      "x": 0.0,
      "y": 0.0,
      "z": -0.0
    },
    "size": {
      "width": 1.5,
      "height": 0.0,
      "depth": 36.77983
    }
  },
  {
    "type": "Plane",
    "name": "Z_Area_2-3_Plane.015",
    "position": {
      "x": 88.50251,
      "y": 0.19921,
      "z": -135.10841
    },
    "rotation": {
      "w": 1.0,
      "x": 0.0,
      "y": 0.0,
      "z": -0.0
    },
    "size": {
      "width": 1.5,
      "height": 0.0,
      "depth": 35.325215
    }
  },
  {
    "type": "Plane",
    "name": "Z_Area_2-3_Plane.016",
    "position": {
      "x": -95.48868,
      "y": 0.19921,
      "z": -269.99426
    },
    "rotation": {
      "w": 1.0,
      "x": 0.0,
      "y": 0.0,
      "z": -0.0
    },
    "size": {
      "width": 1.5,
      "height": 0.0,
      "depth": 13.894685
    }
  },
  {
    "type": "Plane",
    "name": "Z_Area_2-3_Plane.017",
    "position": {
      "x": -95.48868,
      "y": 0.19921,
      "z": -209.99524
    },
    "rotation": {
      "w": 1.0,
      "x": 0.0,
      "y": 0.0,
      "z": -0.0
    },
    "size": {
      "width": 1.5,
      "height": 0.0,
      "depth": 13.894685
    }
  },
  {
    "type": "Plane",
    "name": "Z_Area_2-3_Plane.018",
    "position": {
      "x": -88.50691,
      "y": 0.19921,
      "z": -190.32718
    },
    "rotation": {
      "w": 1.0,
      "x": 0.0,
      "y": 0.0,
      "z": -0.0
    },
    "size": {
      "width": 1.5,
      "height": 0.0,
      "depth": 3.31449
    }
  },
  {
    "type": "Plane",
    "name": "Z_Area_2-3_Plane.019",
    "position": {
      "x": -88.50691,
      "y": 0.19921,
      "z": -289.68051
    },
    "rotation": {
      "w": 1.0,
      "x": 0.0,
      "y": 0.0,
      "z": -0.0
    },
    "size": {
      "width": 1.5,
      "height": 0.0,
      "depth": 3.31032
    }
  },
  {
    "type": "Plane",
    "name": "Z_Area_2-3_Plane.020",
    "position": {
      "x": -91.61196,
      "y": 0.19921,
      "z": -285.40161
    },
    "rotation": {
      "w": 0.85745,
      "x": 0.0,
      "y": -0.51456,
      "z": -0.0
    },
    "size": {
      "width": 1.34231,
      "height": 0.0,
      "depth": 4.549415
    }
  },
  {
    "type": "Plane",
    "name": "Z_Area_2-3_Plane.021",
    "position": {
      "x": -91.61196,
      "y": 0.19921,
      "z": -225.35876
    },
    "rotation": {
      "w": 0.85745,
      "x": 0.0,
      "y": -0.51456,
      "z": -0.0
    },
    "size": {
      "width": 1.34231,
      "height": 0.0,
      "depth": 4.549415
    }
  },
  {
    "type": "Plane",
    "name": "Z_Area_2-3_Plane.022",
    "position": {
      "x": -88.50704,
      "y": 0.19921,
      "z": -240.09418
    },
    "rotation": {
      "w": 1.0,
      "x": 0.0,
      "y": 0.0,
      "z": -0.0
    },
    "size": {
      "width": 1.5,
      "height": 0.0,
      "depth": 13.61218
    }
  },
  {
    "type": "Plane",
    "name": "Z_Area_2-3_Plane.023",
    "position": {
      "x": -91.89345,
      "y": 0.19921,
      "z": -254.83366
    },
    "rotation": {
      "w": 0.51791,
      "x": 0.0,
      "y": -0.85544,
      "z": -0.0
    },
    "size": {
      "width": 1.34231,
      "height": 0.0,
      "depth": 4.549415
    }
  },
  {
    "type": "Plane",
    "name": "Z_Area_2-3_Plane.024",
    "position": {
      "x": -91.89345,
      "y": 0.19921,
      "z": -194.80064
    },
    "rotation": {
      "w": 0.51219,
      "x": 0.0,
      "y": -0.85887,
      "z": -0.0
    },
    "size": {
      "width": 1.36886,
      "height": 0.0,
      "depth": 4.85077
    }
  },
  {
    "type": "Plane",
    "name": "Z_Area_2-3_Plane.025",
    "position": {
      "x": -61.32209,
      "y": 0.19921,
      "z": -111.49619
    },
    "rotation": {
      "w": 1.0,
      "x": 0.0,
      "y": 0.0,
      "z": -0.0
    },
    "size": {
      "width": 41.765855,
      "height": 0.0,
      "depth": 1.5
    }
  },
  {
    "type": "Plane",
    "name": "Z_Area_2-3_Plane.026",
    "position": {
      "x": -45.02384,
      "y": 0.19921,
      "z": -128.49791
    },
    "rotation": {
      "w": 1.0,
      "x": 0.0,
      "y": 0.0,
      "z": -0.0
    },
    "size": {
      "width": 25.201975,
      "height": 0.0,
      "depth": 1.5
    }
  },
  {
    "type": "Plane",
    "name": "Z_Area_2-3_Plane.027",
    "position": {
      "x": -45.02384,
      "y": 0.19921,
      "z": -171.48981
    },
    "rotation": {
      "w": 1.0,
      "x": 0.0,
      "y": 0.0,
      "z": -0.0
    },
    "size": {
      "width": 25.201975,
      "height": 0.0,
      "depth": 1.5
    }
  },
  {
    "type": "Plane",
    "name": "Z_Area_2-3_Plane.028",
    "position": {
      "x": -45.02384,
      "y": 0.19921,
      "z": -188.50273
    },
    "rotation": {
      "w": 1.0,
      "x": 0.0,
      "y": 0.0,
      "z": -0.0
    },
    "size": {
      "width": 25.201975,
      "height": 0.0,
      "depth": 1.5
    }
  },
  {
    "type": "Plane",
    "name": "Z_Area_2-3_Plane.029",
    "position": {
      "x": -45.02384,
      "y": 0.19921,
      "z": -231.50319
    },
    "rotation": {
      "w": 1.0,
      "x": 0.0,
      "y": 0.0,
      "z": -0.0
    },
    "size": {
      "width": 25.201975,
      "height": 0.0,
      "depth": 1.5
    }
  },
  {
    "type": "Plane",
    "name": "Z_Area_2-3_Plane.030",
    "position": {
      "x": -45.02384,
      "y": 0.19921,
      "z": -248.50197
    },
    "rotation": {
      "w": 1.0,
      "x": 0.0,
      "y": 0.0,
      "z": -0.0
    },
    "size": {
      "width": 25.201975,
      "height": 0.0,
      "depth": 1.5
    }
  },
  {
    "type": "Plane",
    "name": "Z_Area_2-3_Plane.031",
    "position": {
      "x": -45.02384,
      "y": 0.19921,
      "z": -291.50076
    },
    "rotation": {
      "w": 1.0,
      "x": 0.0,
      "y": 0.0,
      "z": -0.0
    },
    "size": {
      "width": 25.201975,
      "height": 0.0,
      "depth": 1.5
    }
  },
  {
    "type": "Plane",
    "name": "Z_Area_2-3_Plane.032",
    "position": {
      "x": 45.06586,
      "y": 0.19921,
      "z": -291.50076
    },
    "rotation": {
      "w": 1.0,
      "x": 0.0,
      "y": 0.0,
      "z": -0.0
    },
    "size": {
      "width": 25.201975,
      "height": 0.0,
      "depth": 1.5
    }
  },
  {
    "type": "Plane",
    "name": "Z_Area_2-3_Plane.033",
    "position": {
      "x": 45.06586,
      "y": 0.19921,
      "z": -248.50604
    },
    "rotation": {
      "w": 1.0,
      "x": 0.0,
      "y": 0.0,
      "z": -0.0
    },
    "size": {
      "width": 25.201975,
      "height": 0.0,
      "depth": 1.5
    }
  },
  {
    "type": "Plane",
    "name": "Z_Area_2-3_Plane.034",
    "position": {
      "x": 45.06586,
      "y": 0.19921,
      "z": -231.48756
    },
    "rotation": {
      "w": 1.0,
      "x": 0.0,
      "y": 0.0,
      "z": -0.0
    },
    "size": {
      "width": 25.201975,
      "height": 0.0,
      "depth": 1.5
    }
  },
  {
    "type": "Plane",
    "name": "Z_Area_2-3_Plane.035",
    "position": {
      "x": 45.06586,
      "y": 0.19921,
      "z": -188.49612
    },
    "rotation": {
      "w": 1.0,
      "x": 0.0,
      "y": 0.0,
      "z": -0.0
    },
    "size": {
      "width": 25.201975,
      "height": 0.0,
      "depth": 1.5
    }
  },
  {
    "type": "Plane",
    "name": "Z_Area_2-3_Plane.036",
    "position": {
      "x": 45.06586,
      "y": 0.19921,
      "z": -171.50317
    },
    "rotation": {
      "w": 1.0,
      "x": 0.0,
      "y": 0.0,
      "z": -0.0
    },
    "size": {
      "width": 25.201975,
      "height": 0.0,
      "depth": 1.5
    }
  },
  {
    "type": "Plane",
    "name": "Z_Area_2-3_Plane.037",
    "position": {
      "x": 0.00238,
      "y": 0.19921,
      "z": -134.5076
    },
    "rotation": {
      "w": 1.0,
      "x": 0.0,
      "y": 0.0,
      "z": -0.0
    },
    "size": {
      "width": 1.5,
      "height": 0.0,
      "depth": 35.505025
    }
  },
  {
    "type": "Plane",
    "name": "Z_Area_2-3_Plane.038",
    "position": {
      "x": 0.00434,
      "y": 0.19921,
      "z": -210.01115
    },
    "rotation": {
      "w": 1.0,
      "x": 0.0,
      "y": 0.0,
      "z": -0.0
    },
    "size": {
      "width": 1.5,
      "height": 0.0,
      "depth": 19.98745
    }
  },
  {
    "type": "Plane",
    "name": "Z_Area_2-3_Plane.039",
    "position": {
      "x": -18.49632,
      "y": 0.19921,
      "z": -224.98965
    },
    "rotation": {
      "w": 1.0,
      "x": 0.0,
      "y": 0.0,
      "z": -0.0
    },
    "size": {
      "width": 1.5,
      "height": 0.0,
      "depth": 7.98553
    }
  },
  {
    "type": "Plane",
    "name": "Z_Area_2-3_Plane.040",
    "position": {
      "x": -18.49632,
      "y": 0.19921,
      "z": -195.00504
    },
    "rotation": {
      "w": 1.0,
      "x": 0.0,
      "y": 0.0,
      "z": -0.0
    },
    "size": {
      "width": 1.5,
      "height": 0.0,
      "depth": 7.98553
    }
  },
  {
    "type": "Plane",
    "name": "Z_Area_2-3_Plane.041",
    "position": {
      "x": -57.49385,
      "y": 0.25066,
      "z": -286.31946
    },
    "rotation": {
      "w": 1.0,
      "x": 0.0,
      "y": 0.0,
      "z": -0.0
    },
    "size": {
      "width": 12.53329,
      "height": 0.0,
      "depth": 3.82167
    }
  },
  {
    "type": "Plane",
    "name": "Z_Area_2-3_Plane.042",
    "position": {
      "x": -57.49385,
      "y": 0.25066,
      "z": -253.66879
    },
    "rotation": {
      "w": 1.0,
      "x": 0.0,
      "y": 0.0,
      "z": -0.0
    },
    "size": {
      "width": 12.53329,
      "height": 0.0,
      "depth": 3.82167
    }
  },
  {
    "type": "Plane",
    "name": "Z_Area_2-3_Plane.043",
    "position": {
      "x": -32.50665,
      "y": 0.25066,
      "z": -226.31566
    },
    "rotation": {
      "w": 1.0,
      "x": 0.0,
      "y": 0.0,
      "z": -0.0
    },
    "size": {
      "width": 12.53329,
      "height": 0.0,
      "depth": 3.82167
    }
  },
  {
    "type": "Plane",
    "name": "Z_Area_2-3_Plane.044",
    "position": {
      "x": -32.50665,
      "y": 0.25066,
      "z": -193.69151
    },
    "rotation": {
      "w": 1.0,
      "x": 0.0,
      "y": 0.0,
      "z": -0.0
    },
    "size": {
      "width": 12.53329,
      "height": 0.0,
      "depth": 3.82167
    }
  },
  {
    "type": "Plane",
    "name": "Z_Area_2-3_Plane.045",
    "position": {
      "x": 92.97808,
      "y": 0.25066,
      "z": -239.96176
    },
    "rotation": {
      "w": 1.0,
      "x": 0.0,
      "y": 0.0,
      "z": -0.0
    },
    "size": {
      "width": 3.001695,
      "height": 0.0,
      "depth": 19.97888
    }
  },
  {
    "type": "Plane",
    "name": "Z_Area_2-3_Plane.046",
    "position": {
      "x": -32.93621,
      "y": 0.66821,
      "z": -286.12244
    },
    "rotation": {
      "w": 1.0,
      "x": 0.0,
      "y": 0.0,
      "z": -0.0
    },
    "size": {
      "width": 8.46638,
      "height": 0.0,
      "depth": 2.70258
    }
  },
  {
    "type": "Plane",
    "name": "Z_Area_2-3_Plane.047",
    "position": {
      "x": -32.93621,
      "y": 7.79617,
      "z": -285.58603
    },
    "rotation": {
      "w": 1.0,
      "x": 0.0,
      "y": 0.0,
      "z": -0.0
    },
    "size": {
      "width": 7.50958,
      "height": 0.0,
      "depth": 2.02207
    }
  },
  {
    "type": "Solid",
    "name": "Z_Area_2-3_Solid.001",
    "position": {
      "x": -97.56136,
      "y": 3.29801,
      "z": -282.71646
    },
    "rotation": {
      "w": 1.0,
      "x": 0.0,
      "y": 0.0,
      "z": -0.0
    },
    "size": {
      "width": 0.40732,
      "height": 2.936215,
      "depth": 0.395985
    }
  },
  {
    "type": "Solid",
    "name": "Z_Area_2-3_Solid.002",
    "position": {
      "x": -97.56136,
      "y": 3.29801,
      "z": -197.24017
    },
    "rotation": {
      "w": 1.0,
      "x": 0.0,
      "y": 0.0,
      "z": -0.0
    },
    "size": {
      "width": 0.40732,
      "height": 2.936215,
      "depth": 0.395985
    }
  },
  {
    "type": "Solid",
    "name": "Z_Area_2-3_Solid.003",
    "position": {
      "x": -95.2907,
      "y": 2.30644,
      "z": -209.97046
    },
    "rotation": {
      "w": 1.0,
      "x": 0.0,
      "y": 0.0,
      "z": -0.0
    },
    "size": {
      "width": 1.039385,
      "height": 2.254885,
      "depth": 4.48093
    }
  },
  {
    "type": "Solid",
    "name": "Z_Area_2-3_Solid.004",
    "position": {
      "x": -95.2907,
      "y": 2.30644,
      "z": -270.0206
    },
    "rotation": {
      "w": 1.0,
      "x": 0.0,
      "y": 0.0,
      "z": -0.0
    },
    "size": {
      "width": 1.039385,
      "height": 2.254885,
      "depth": 4.48093
    }
  },
  {
    "type": "Solid",
    "name": "Z_Area_2-3_Solid.005",
    "position": {
      "x": -101.25938,
      "y": 0.9113,
      "z": -218.72879
    },
    "rotation": {
      "w": 1.0,
      "x": 0.0,
      "y": 0.0,
      "z": -0.0
    },
    "size": {
      "width": 0.468505,
      "height": 0.541405,
      "depth": 1.874345
    }
  },
  {
    "type": "Solid",
    "name": "Z_Area_2-3_Solid.006",
    "position": {
      "x": -87.76649,
      "y": 0.70586,
      "z": -229.32491
    },
    "rotation": {
      "w": 1.0,
      "x": 0.0,
      "y": 0.0,
      "z": -0.0
    },
    "size": {
      "width": 0.15,
      "height": 0.35,
      "depth": 0.15
    }
  },
  {
    "type": "Solid",
    "name": "Z_Area_2-3_Solid.007",
    "position": {
      "x": -88.54608,
      "y": 0.70586,
      "z": -187.44519
    },
    "rotation": {
      "w": 1.0,
      "x": 0.0,
      "y": 0.0,
      "z": -0.0
    },
    "size": {
      "width": 0.15,
      "height": 0.35,
      "depth": 0.15
    }
  },
  {
    "type": "Solid",
    "name": "Z_Area_2-3_Solid.008",
    "position": {
      "x": -65.0409,
      "y": 3.29801,
      "z": -286.44073
    },
    "rotation": {
      "w": 1.0,
      "x": 0.0,
      "y": 0.0,
      "z": -0.0
    },
    "size": {
      "width": 0.40732,
      "height": 2.936215,
      "depth": 0.395985
    }
  },
  {
    "type": "Solid",
    "name": "Z_Area_2-3_Solid.009",
    "position": {
      "x": -57.54342,
      "y": 3.29801,
      "z": -286.44073
    },
    "rotation": {
      "w": 1.0,
      "x": 0.0,
      "y": 0.0,
      "z": -0.0
    },
    "size": {
      "width": 0.40732,
      "height": 2.936215,
      "depth": 0.395985
    }
  },
  {
    "type": "Solid",
    "name": "Z_Area_2-3_Solid.010",
    "position": {
      "x": -50.04818,
      "y": 3.29801,
      "z": -286.44073
    },
    "rotation": {
      "w": 1.0,
      "x": 0.0,
      "y": 0.0,
      "z": -0.0
    },
    "size": {
      "width": 0.40732,
      "height": 2.936215,
      "depth": 0.395985
    }
  },
  {
    "type": "Solid",
    "name": "Z_Area_2-3_Solid.011",
    "position": {
      "x": -25.0216,
      "y": 3.29801,
      "z": -226.4346
    },
    "rotation": {
      "w": 1.0,
      "x": 0.0,
      "y": 0.0,
      "z": -0.0
    },
    "size": {
      "width": 0.40732,
      "height": 2.936215,
      "depth": 0.395985
    }
  },
  {
    "type": "Solid",
    "name": "Z_Area_2-3_Solid.012",
    "position": {
      "x": -32.56182,
      "y": 3.29801,
      "z": -226.4346
    },
    "rotation": {
      "w": 1.0,
      "x": 0.0,
      "y": 0.0,
      "z": -0.0
    },
    "size": {
      "width": 0.40732,
      "height": 2.936215,
      "depth": 0.395985
    }
  },
  {
    "type": "Solid",
    "name": "Z_Area_2-3_Solid.013",
    "position": {
      "x": -40.03437,
      "y": 3.29801,
      "z": -226.4346
    },
    "rotation": {
      "w": 1.0,
      "x": 0.0,
      "y": 0.0,
      "z": -0.0
    },
    "size": {
      "width": 0.40732,
      "height": 2.936215,
      "depth": 0.395985
    }
  },
  {
    "type": "Solid",
    "name": "Z_Area_2-3_Solid.014",
    "position": {
      "x": -65.03242,
      "y": 3.29801,
      "z": -253.65446
    },
    "rotation": {
      "w": 1.0,
      "x": 0.0,
      "y": 0.0,
      "z": -0.0
    },
    "size": {
      "width": 0.40732,
      "height": 2.936215,
      "depth": 0.395985
    }
  },
  {
    "type": "Solid",
    "name": "Z_Area_2-3_Solid.015",
    "position": {
      "x": -57.49577,
      "y": 3.29801,
      "z": -253.65446
    },
    "rotation": {
      "w": 1.0,
      "x": 0.0,
      "y": 0.0,
      "z": -0.0
    },
    "size": {
      "width": 0.40732,
      "height": 2.936215,
      "depth": 0.395985
    }
  },
  {
    "type": "Solid",
    "name": "Z_Area_2-3_Solid.016",
    "position": {
      "x": -50.02549,
      "y": 3.29801,
      "z": -253.65446
    },
    "rotation": {
      "w": 1.0,
      "x": 0.0,
      "y": 0.0,
      "z": -0.0
    },
    "size": {
      "width": 0.40732,
      "height": 2.936215,
      "depth": 0.395985
    }
  },
  {
    "type": "Solid",
    "name": "Z_Area_2-3_Solid.017",
    "position": {
      "x": -25.0216,
      "y": 3.29801,
      "z": -193.67084
    },
    "rotation": {
      "w": 1.0,
      "x": 0.0,
      "y": 0.0,
      "z": -0.0
    },
    "size": {
      "width": 0.40732,
      "height": 2.936215,
      "depth": 0.395985
    }
  },
  {
    "type": "Solid",
    "name": "Z_Area_2-3_Solid.018",
    "position": {
      "x": -32.5089,
      "y": 3.29801,
      "z": -193.67084
    },
    "rotation": {
      "w": 1.0,
      "x": 0.0,
      "y": 0.0,
      "z": -0.0
    },
    "size": {
      "width": 0.40732,
      "height": 2.936215,
      "depth": 0.395985
    }
  },
  {
    "type": "Solid",
    "name": "Z_Area_2-3_Solid.019",
    "position": {
      "x": -40.00474,
      "y": 3.29801,
      "z": -193.67084
    },
    "rotation": {
      "w": 1.0,
      "x": 0.0,
      "y": 0.0,
      "z": -0.0
    },
    "size": {
      "width": 0.40732,
      "height": 2.936215,
      "depth": 0.395985
    }
  },
  {
    "type": "Solid",
    "name": "Z_Area_2-3_Solid.020",
    "position": {
      "x": 93.18698,
      "y": 3.29801,
      "z": -225.03728
    },
    "rotation": {
      "w": 1.0,
      "x": 0.0,
      "y": 0.0,
      "z": -0.0
    },
    "size": {
      "width": 0.40732,
      "height": 2.936215,
      "depth": 0.395985
    }
  },
  {
    "type": "Solid",
    "name": "Z_Area_2-3_Solid.021",
    "position": {
      "x": 93.18698,
      "y": 3.29801,
      "z": -234.66917
    },
    "rotation": {
      "w": 1.0,
      "x": 0.0,
      "y": 0.0,
      "z": -0.0
    },
    "size": {
      "width": 0.40732,
      "height": 2.936215,
      "depth": 0.395985
    }
  },
  {
    "type": "Solid",
    "name": "Z_Area_2-3_Solid.022",
    "position": {
      "x": 93.18698,
      "y": 3.29801,
      "z": -244.73643
    },
    "rotation": {
      "w": 1.0,
      "x": 0.0,
      "y": 0.0,
      "z": -0.0
    },
    "size": {
      "width": 0.40732,
      "height": 2.936215,
      "depth": 0.395985
    }
  },
  {
    "type": "Solid",
    "name": "Z_Area_2-3_Solid.023",
    "position": {
      "x": 93.18698,
      "y": 3.29801,
      "z": -254.3934
    },
    "rotation": {
      "w": 1.0,
      "x": 0.0,
      "y": 0.0,
      "z": -0.0
    },
    "size": {
      "width": 0.40732,
      "height": 2.936215,
      "depth": 0.395985
    }
  },
  {
    "type": "Solid",
    "name": "Z_Area_2-3_Solid.024",
    "position": {
      "x": 88.48801,
      "y": 4.00771,
      "z": -279.98203
    },
    "rotation": {
      "w": 1.0,
      "x": 0.0,
      "y": 0.0,
      "z": -0.0
    },
    "size": {
      "width": 0.2,
      "height": 3.59591,
      "depth": 0.2
    }
  },
  {
    "type": "Solid",
    "name": "Z_Area_2-3_Solid.025",
    "position": {
      "x": 0.01334,
      "y": 3.31959,
      "z": -338.06616
    },
    "rotation": {
      "w": 1.0,
      "x": 0.0,
      "y": 0.0,
      "z": -0.0
    },
    "size": {
      "width": 0.2,
      "height": 2.93445,
      "depth": 0.2
    }
  },
  {
    "type": "Solid",
    "name": "Z_Area_2-3_Solid.026",
    "position": {
      "x": 0.01334,
      "y": 3.31959,
      "z": -201.04614
    },
    "rotation": {
      "w": 1.0,
      "x": 0.0,
      "y": 0.0,
      "z": -0.0
    },
    "size": {
      "width": 0.2,
      "height": 2.93445,
      "depth": 0.2
    }
  },
  {
    "type": "Solid",
    "name": "Z_Area_2-3_Solid.027",
    "position": {
      "x": 0.01334,
      "y": 3.31959,
      "z": -136.00699
    },
    "rotation": {
      "w": 1.0,
      "x": 0.0,
      "y": 0.0,
      "z": -0.0
    },
    "size": {
      "width": 0.2,
      "height": 2.93445,
      "depth": 0.2
    }
  },
  {
    "type": "Solid",
    "name": "Z_Area_2-3_Solid.028",
    "position": {
      "x": -71.31445,
      "y": 0.70586,
      "z": -187.44519
    },
    "rotation": {
      "w": 1.0,
      "x": 0.0,
      "y": 0.0,
      "z": -0.0
    },
    "size": {
      "width": 0.15,
      "height": 0.35,
      "depth": 0.15
    }
  },
  {
    "type": "Solid",
    "name": "Z_Area_2-3_Solid.029",
    "position": {
      "x": -71.31445,
      "y": 0.70586,
      "z": -127.41863
    },
    "rotation": {
      "w": 1.0,
      "x": 0.0,
      "y": 0.0,
      "z": -0.0
    },
    "size": {
      "width": 0.15,
      "height": 0.35,
      "depth": 0.15
    }
  },
  {
    "type": "Solid",
    "name": "Z_Area_2-3_Solid.030",
    "position": {
      "x": -72.31017,
      "y": 0.70586,
      "z": -290.56488
    },
    "rotation": {
      "w": 1.0,
      "x": 0.0,
      "y": 0.0,
      "z": -0.0
    },
    "size": {
      "width": 0.15,
      "height": 0.35,
      "depth": 0.15
    }
  },
  {
    "type": "Solid",
    "name": "Z_Area_2-3_Solid.031",
    "position": {
      "x": 17.54753,
      "y": 0.70586,
      "z": -291.64624
    },
    "rotation": {
      "w": 1.0,
      "x": 0.0,
      "y": 0.0,
      "z": -0.0
    },
    "size": {
      "width": 0.15,
      "height": 0.35,
      "depth": 0.15
    }
  },
  {
    "type": "Solid",
    "name": "Z_Area_2-3_Solid.032",
    "position": {
      "x": 17.54753,
      "y": 0.70586,
      "z": -249.24153
    },
    "rotation": {
      "w": 1.0,
      "x": 0.0,
      "y": 0.0,
      "z": -0.0
    },
    "size": {
      "width": 0.15,
      "height": 0.35,
      "depth": 0.15
    }
  },
  {
    "type": "Solid",
    "name": "Z_Area_2-3_Solid.033",
    "position": {
      "x": -17.41172,
      "y": 0.70586,
      "z": -249.12907
    },
    "rotation": {
      "w": 1.0,
      "x": 0.0,
      "y": 0.0,
      "z": -0.0
    },
    "size": {
      "width": 0.15,
      "height": 0.35,
      "depth": 0.15
    }
  },
  {
    "type": "Solid",
    "name": "Z_Area_2-3_Solid.034",
    "position": {
      "x": -17.41172,
      "y": 0.70586,
      "z": -227.63623
    },
    "rotation": {
      "w": 1.0,
      "x": 0.0,
      "y": 0.0,
      "z": -0.0
    },
    "size": {
      "width": 0.15,
      "height": 0.35,
      "depth": 0.15
    }
  },
  {
    "type": "Solid",
    "name": "Z_Area_2-3_Solid.035",
    "position": {
      "x": -17.41172,
      "y": 0.70586,
      "z": -188.80357
    },
    "rotation": {
      "w": 1.0,
      "x": 0.0,
      "y": 0.0,
      "z": -0.0
    },
    "size": {
      "width": 0.15,
      "height": 0.35,
      "depth": 0.15
    }
  },
  {
    "type": "Solid",
    "name": "Z_Area_2-3_Solid.036",
    "position": {
      "x": -17.41172,
      "y": 0.70586,
      "z": -129.10455
    },
    "rotation": {
      "w": 1.0,
      "x": 0.0,
      "y": 0.0,
      "z": -0.0
    },
    "size": {
      "width": 0.15,
      "height": 0.35,
      "depth": 0.15
    }
  },
  {
    "type": "Solid",
    "name": "Z_Area_2-3_Solid.037",
    "position": {
      "x": 45.14577,
      "y": 5.40732,
      "z": -133.10281
    },
    "rotation": {
      "w": 1.0,
      "x": 0.0,
      "y": 0.0,
      "z": -0.0
    },
    "size": {
      "width": 23.419485,
      "height": 5.0,
      "depth": 34.99837
    }
  },
  {
    "type": "Solid",
    "name": "Z_Area_2-3_Solid.038",
    "position": {
      "x": 49.34557,
      "y": 8.60024,
      "z": -195.83914
    },
    "rotation": {
      "w": 1.0,
      "x": 0.0,
      "y": 0.0,
      "z": -0.0
    },
    "size": {
      "width": 10.49467,
      "height": 8.62598,
      "depth": 5.07285
    }
  },
  {
    "type": "Solid",
    "name": "Z_Area_2-3_Solid.039",
    "position": {
      "x": 60.22047,
      "y": 8.72598,
      "z": -204.3813
    },
    "rotation": {
      "w": 1.0,
      "x": 0.0,
      "y": 0.0,
      "z": -0.0
    },
    "size": {
      "width": 8.77479,
      "height": 8.508525,
      "depth": 4.161075
    }
  },
  {
    "type": "Solid",
    "name": "Z_Area_2-3_Solid.040",
    "position": {
      "x": 34.37352,
      "y": 8.60024,
      "z": -220.61311
    },
    "rotation": {
      "w": 1.0,
      "x": 0.0,
      "y": 0.0,
      "z": -0.0
    },
    "size": {
      "width": 4.1716,
      "height": 8.62598,
      "depth": 9.0528
    }
  },
  {
    "type": "Solid",
    "name": "Z_Area_2-3_Solid.041",
    "position": {
      "x": 25.64226,
      "y": 8.60024,
      "z": -216.00015
    },
    "rotation": {
      "w": 1.0,
      "x": 0.0,
      "y": 0.0,
      "z": -0.0
    },
    "size": {
      "width": 4.72607,
      "height": 8.62598,
      "depth": 4.17466
    }
  },
  {
    "type": "Solid",
    "name": "Z_Area_2-3_Solid.042",
    "position": {
      "x": 29.56714,
      "y": 13.49526,
      "z": -201.94144
    },
    "rotation": {
      "w": 1.0,
      "x": 0.0,
      "y": 0.0,
      "z": -0.0
    },
    "size": {
      "width": 6.96018,
      "height": 13.260755,
      "depth": 9.66812
    }
  },
  {
    "type": "Solid",
    "name": "Z_Area_2-3_Solid.043",
    "position": {
      "x": 21.7515,
      "y": 13.49526,
      "z": -203.62393
    },
    "rotation": {
      "w": 1.0,
      "x": 0.0,
      "y": 0.0,
      "z": -0.0
    },
    "size": {
      "width": 0.91028,
      "height": 13.260755,
      "depth": 6.08856
    }
  },
  {
    "type": "Solid",
    "name": "Z_Area_2-3_Solid.044",
    "position": {
      "x": 29.51373,
      "y": 13.49526,
      "z": -191.50087
    },
    "rotation": {
      "w": 1.0,
      "x": 0.0,
      "y": 0.0,
      "z": -0.0
    },
    "size": {
      "width": 3.477985,
      "height": 13.260755,
      "depth": 0.97346
    }
  },
  {
    "type": "Solid",
    "name": "Z_Area_2-3_Solid.045",
    "position": {
      "x": 58.67612,
      "y": 6.30024,
      "z": -220.33342
    },
    "rotation": {
      "w": 1.0,
      "x": 0.0,
      "y": 0.0,
      "z": -0.0
    },
    "size": {
      "width": 9.655125,
      "height": 6.18205,
      "depth": 4.80263
    }
  },
  {
    "type": "Solid",
    "name": "Z_Area_2-3_Solid.046",
    "position": {
      "x": -32.22569,
      "y": 11.00685,
      "z": -259.14905
    },
    "rotation": {
      "w": 0.70713,
      "x": 0.0,
      "y": -0.70708,
      "z": -0.0
    },
    "size": {
      "width": 8.0,
      "height": 11.14538,
      "depth": 7.9
    }
  },
  {
    "type": "Solid",
    "name": "Z_Area_2-3_Solid.047",
    "position": {
      "x": -32.22569,
      "y": 11.00685,
      "z": -259.14905
    },
    "rotation": {
      "w": 0.70713,
      "x": 0.0,
      "y": -0.70708,
      "z": -0.0
    },
    "size": {
      "width": 4.04388,
      "height": 11.14538,
      "depth": 11.28644
    }
  },
  {
    "type": "Solid",
    "name": "Z_Area_2-3_Solid.048",
    "position": {
      "x": 29.93957,
      "y": 11.00685,
      "z": -277.96347
    },
    "rotation": {
      "w": -0.0,
      "x": 0.0,
      "y": -1.0,
      "z": -0.0
    },
    "size": {
      "width": 4.04388,
      "height": 11.14538,
      "depth": 11.28644
    }
  },
  {
    "type": "Solid",
    "name": "Z_Area_2-3_Solid.049",
    "position": {
      "x": 29.93957,
      "y": 11.00685,
      "z": -277.96347
    },
    "rotation": {
      "w": -0.0,
      "x": 0.0,
      "y": -1.0,
      "z": -0.0
    },
    "size": {
      "width": 8.0,
      "height": 11.14538,
      "depth": 7.9
    }
  },
  {
    "type": "Solid",
    "name": "Z_Area_2-3_Solid.050",
    "position": {
      "x": 33.52172,
      "y": 4.93685,
      "z": -257.30298
    },
    "rotation": {
      "w": -0.0,
      "x": 0.0,
      "y": -1.0,
      "z": -0.0
    },
    "size": {
      "width": 11.94522,
      "height": 4.579925,
      "depth": 5.90692
    }
  },
  {
    "type": "Solid",
    "name": "Z_Area_2-3_Solid.051",
    "position": {
      "x": 60.31493,
      "y": 6.60852,
      "z": -260.5545
    },
    "rotation": {
      "w": -0.0,
      "x": 0.0,
      "y": -1.0,
      "z": -0.0
    },
    "size": {
      "width": 7.787235,
      "height": 6.399965,
      "depth": 8.6721
    }
  },
  {
    "type": "Solid",
    "name": "Z_Area_2-3_Solid.052",
    "position": {
      "x": 58.81052,
      "y": 5.49011,
      "z": -280.46979
    },
    "rotation": {
      "w": -0.0,
      "x": 0.0,
      "y": -1.0,
      "z": -0.0
    },
    "size": {
      "width": 9.598415,
      "height": 5.26315,
      "depth": 6.98764
    }
  },
  {
    "type": "Solid",
    "name": "Z_Area_2-3_Solid.053",
    "position": {
      "x": 60.56344,
      "y": 5.49011,
      "z": -288.3248
    },
    "rotation": {
      "w": -0.0,
      "x": 0.0,
      "y": -1.0,
      "z": -0.0
    },
    "size": {
      "width": 6.043355,
      "height": 5.26315,
      "depth": 0.874525
    }
  },
  {
    "type": "Solid",
    "name": "Z_Area_2-3_Solid.054",
    "position": {
      "x": 48.49047,
      "y": 5.49011,
      "z": -280.45013
    },
    "rotation": {
      "w": -0.0,
      "x": 0.0,
      "y": -1.0,
      "z": -0.0
    },
    "size": {
      "width": 1.03086,
      "height": 5.26315,
      "depth": 3.50612
    }
  },
  {
    "type": "Solid",
    "name": "Z_Area_2-3_Solid.055",
    "position": {
      "x": -32.91429,
      "y": 5.74319,
      "z": -276.07654
    },
    "rotation": {
      "w": -0.0,
      "x": 0.0,
      "y": -1.0,
      "z": -0.0
    },
    "size": {
      "width": 11.66977,
      "height": 5.38745,
      "depth": 6.9838
    }
  },
  {
    "type": "Solid",
    "name": "Z_Area_2-3_Solid.056",
    "position": {
      "x": -26.32406,
      "y": 4.10087,
      "z": -286.96658
    },
    "rotation": {
      "w": 1.0,
      "x": 0.0,
      "y": 0.0,
      "z": -0.0
    },
    "size": {
      "width": 0.3,
      "height": 3.16478,
      "depth": 0.3
    }
  },
  {
    "type": "Solid",
    "name": "Z_Area_2-3_Solid.057",
    "position": {
      "x": -30.57304,
      "y": 4.10087,
      "z": -286.87177
    },
    "rotation": {
      "w": 1.0,
      "x": 0.0,
      "y": 0.0,
      "z": -0.0
    },
    "size": {
      "width": 0.3,
      "height": 3.16478,
      "depth": 0.3
    }
  },
  {
    "type": "Solid",
    "name": "Z_Area_2-3_Solid.058",
    "position": {
      "x": -35.27939,
      "y": 4.10087,
      "z": -286.87177
    },
    "rotation": {
      "w": 1.0,
      "x": 0.0,
      "y": 0.0,
      "z": -0.0
    },
    "size": {
      "width": 0.3,
      "height": 3.16478,
      "depth": 0.3
    }
  },
  {
    "type": "Solid",
    "name": "Z_Area_2-3_Solid.059",
    "position": {
      "x": -39.52839,
      "y": 4.10087,
      "z": -286.87177
    },
    "rotation": {
      "w": 1.0,
      "x": 0.0,
      "y": 0.0,
      "z": -0.0
    },
    "size": {
      "width": 0.3,
      "height": 3.16478,
      "depth": 0.3
    }
  },
  {
    "type": "Solid",
    "name": "Z_Area_2-3_Solid.060",
    "position": {
      "x": -52.88809,
      "y": 5.74319,
      "z": -270.23788
    },
    "rotation": {
      "w": -0.0,
      "x": 0.0,
      "y": -1.0,
      "z": -0.0
    },
    "size": {
      "width": 5.522645,
      "height": 4.96593,
      "depth": 10.95404
    }
  },
  {
    "type": "Solid",
    "name": "Z_Area_2-3_Solid.061",
    "position": {
      "x": -39.24088,
      "y": 5.74319,
      "z": -210.14354
    },
    "rotation": {
      "w": -0.0,
      "x": 0.0,
      "y": -1.0,
      "z": -0.0
    },
    "size": {
      "width": 5.522645,
      "height": 4.96593,
      "depth": 10.95404
    }
  },
  {
    "type": "Solid",
    "name": "Z_Area_2-3_Solid.062",
    "position": {
      "x": -32.1911,
      "y": 2.3426,
      "z": -216.66142
    },
    "rotation": {
      "w": 1.0,
      "x": 0.0,
      "y": 0.0,
      "z": -0.0
    },
    "size": {
      "width": 0.1841,
      "height": 1.78499,
      "depth": 0.16386
    }
  },
  {
    "type": "Solid",
    "name": "Z_Area_2-3_Solid.063",
    "position": {
      "x": -32.19681,
      "y": 2.3426,
      "z": -219.77927
    },
    "rotation": {
      "w": 1.0,
      "x": 0.0,
      "y": 0.0,
      "z": -0.0
    },
    "size": {
      "width": 0.1841,
      "height": 1.78499,
      "depth": 0.16386
    }
  },
  {
    "type": "Solid",
    "name": "Z_Area_2-3_Solid.064",
    "position": {
      "x": -58.44916,
      "y": 2.73978,
      "z": -225.0087
    },
    "rotation": {
      "w": 1.0,
      "x": 0.0,
      "y": 0.0,
      "z": -0.0
    },
    "size": {
      "width": 9.927635,
      "height": 2.769445,
      "depth": 3.934105
    }
  },
  {
    "type": "Solid",
    "name": "Z_Area_2-3_Solid.065",
    "position": {
      "x": -55.65747,
      "y": 2.32643,
      "z": -216.7865
    },
    "rotation": {
      "w": 1.0,
      "x": 0.0,
      "y": 0.0,
      "z": -0.0
    },
    "size": {
      "width": 0.49201,
      "height": 2.18588,
      "depth": 0.46922
    }
  },
  {
    "type": "Solid",
    "name": "Z_Area_2-3_Solid.066",
    "position": {
      "x": -49.1711,
      "y": 2.32643,
      "z": -216.7865
    },
    "rotation": {
      "w": 1.0,
      "x": 0.0,
      "y": 0.0,
      "z": -0.0
    },
    "size": {
      "width": 0.49201,
      "height": 2.18588,
      "depth": 0.46922
    }
  },
  {
    "type": "Solid",
    "name": "Z_Area_2-3_Solid.067",
    "position": {
      "x": -52.41878,
      "y": 5.03351,
      "z": -218.51517
    },
    "rotation": {
      "w": 1.0,
      "x": 0.0,
      "y": 0.0,
      "z": -0.0
    },
    "size": {
      "width": 3.99516,
      "height": 0.47416,
      "depth": 2.5078
    }
  },
  {
    "type": "Solid",
    "name": "Z_Area_2-3_Solid.068",
    "position": {
      "x": -23.86041,
      "y": 3.99325,
      "z": -188.55145
    },
    "rotation": {
      "w": 1.0,
      "x": 0.0,
      "y": 0.0,
      "z": -0.0
    },
    "size": {
      "width": 0.2,
      "height": 3.64334,
      "depth": 0.2
    }
  },
  {
    "type": "Solid",
    "name": "Z_Area_2-3_Solid.069",
    "position": {
      "x": -54.3399,
      "y": 5.74319,
      "z": -138.67403
    },
    "rotation": {
      "w": -0.70714,
      "x": 0.0,
      "y": -0.70708,
      "z": -0.0
    },
    "size": {
      "width": 5.52264,
      "height": 4.96593,
      "depth": 10.95404
    }
  },
  {
    "type": "Solid",
    "name": "Z_Area_2-3_Solid.070",
    "position": {
      "x": -54.3399,
      "y": 6.73674,
      "z": -155.84639
    },
    "rotation": {
      "w": -0.70714,
      "x": 0.0,
      "y": -0.70708,
      "z": -0.0
    },
    "size": {
      "width": 5.9541,
      "height": 6.761675,
      "depth": 11.93867
    }
  },
  {
    "type": "Solid",
    "name": "Z_Area_2-3_Solid.071",
    "position": {
      "x": -48.80854,
      "y": 2.87052,
      "z": -164.15634
    },
    "rotation": {
      "w": -0.70714,
      "x": 0.0,
      "y": -0.70708,
      "z": -0.0
    },
    "size": {
      "width": 2.75287,
      "height": 2.878865,
      "depth": 6.361515
    }
  },
  {
    "type": "Solid",
    "name": "Z_Area_2-3_Solid.072",
    "position": {
      "x": -56.9769,
      "y": 2.87052,
      "z": -164.85378
    },
    "rotation": {
      "w": -0.92478,
      "x": 0.0,
      "y": -0.38051,
      "z": -0.0
    },
    "size": {
      "width": 2.75287,
      "height": 2.878865,
      "depth": 0.144455
    }
  },
  {
    "type": "Solid",
    "name": "Z_Area_2-3_Solid.073",
    "position": {
      "x": -29.61107,
      "y": 6.62092,
      "z": -140.05809
    },
    "rotation": {
      "w": -0.70714,
      "x": 0.0,
      "y": -0.70708,
      "z": -0.0
    },
    "size": {
      "width": 6.522795,
      "height": 6.377415,
      "depth": 8.71279
    }
  },
  {
    "type": "Solid",
    "name": "Z_Area_2-3_Solid.074",
    "position": {
      "x": -34.90024,
      "y": 6.62092,
      "z": -132.38303
    },
    "rotation": {
      "w": -0.70714,
      "x": 0.0,
      "y": -0.70708,
      "z": -0.0
    },
    "size": {
      "width": 1.333585,
      "height": 6.377415,
      "depth": 3.463025
    }
  },
  {
    "type": "Solid",
    "name": "Z_Area_2-3_Solid.075",
    "position": {
      "x": -21.65555,
      "y": 1.64444,
      "z": -161.36494
    },
    "rotation": {
      "w": 1.0,
      "x": 0.0,
      "y": 0.0,
      "z": -0.0
    },
    "size": {
      "width": 0.33774,
      "height": 1.593475,
      "depth": 0.327405
    }
  },
  {
    "type": "Solid",
    "name": "Z_Area_2-3_Solid.076",
    "position": {
      "x": -21.65555,
      "y": 1.64444,
      "z": -156.12476
    },
    "rotation": {
      "w": 1.0,
      "x": 0.0,
      "y": 0.0,
      "z": -0.0
    },
    "size": {
      "width": 0.33774,
      "height": 1.593475,
      "depth": 0.327405
    }
  },
  {
    "type": "Solid",
    "name": "Z_Area_2-3_Solid.077",
    "position": {
      "x": -22.99465,
      "y": 3.58866,
      "z": -158.76286
    },
    "rotation": {
      "w": 1.0,
      "x": 0.0,
      "y": 0.0,
      "z": -0.0
    },
    "size": {
      "width": 2.180575,
      "height": 0.339205,
      "depth": 3.46126
    }
  },
  {
    "type": "Solid",
    "name": "Z_Area_2-3_Solid.078",
    "position": {
      "x": -27.87762,
      "y": 8.86735,
      "z": -158.72008
    },
    "rotation": {
      "w": -0.70714,
      "x": 0.0,
      "y": -0.70708,
      "z": -0.0
    },
    "size": {
      "width": 8.72634,
      "height": 9.07579,
      "depth": 2.711365
    }
  },
  {
    "type": "Solid",
    "name": "Z_Area_2-3_Solid.079",
    "position": {
      "x": -34.42107,
      "y": 8.86735,
      "z": -158.72008
    },
    "rotation": {
      "w": -0.70714,
      "x": 0.0,
      "y": -0.70708,
      "z": -0.0
    },
    "size": {
      "width": 10.46571,
      "height": 9.07579,
      "depth": 3.847815
    }
  }
]
